mospy/GUI.py
mospy/__init__.py
mospy/command_line.py
mospy/mosaic.py
mospy/show_images.py
mospy-1.0.0.dist-info/DESCRIPTION.rst
mospy-1.0.0.dist-info/METADATA
mospy-1.0.0.dist-info/RECORD
mospy-1.0.0.dist-info/WHEEL
mospy-1.0.0.dist-info/entry_points.txt
mospy-1.0.0.dist-info/metadata.json
mospy-1.0.0.dist-info/top_level.txt
pymos/GUI.py
pymos/__init__.py
pymos/command_line.py
pymos/mosaic.py
pymos/show_images.py
